{"stats":{"minecraft:custom":{"minecraft:interact_with_furnace":8,"minecraft:mob_kills":8,"minecraft:interact_with_crafting_table":34,"minecraft:play_one_minute":63770,"minecraft:leave_game":5,"minecraft:time_since_death":47757,"minecraft:time_since_rest":47777,"minecraft:sprint_one_cm":165140,"minecraft:damage_taken":381,"minecraft:walk_one_cm":331158,"minecraft:drop":7,"minecraft:damage_dealt":1886,"minecraft:swim_one_cm":3881,"minecraft:fly_one_cm":560,"minecraft:open_chest":10,"minecraft:crouch_one_cm":1008,"minecraft:deaths":1,"minecraft:sneak_time":335,"minecraft:walk_under_water_one_cm":4415,"minecraft:walk_on_water_one_cm":2221},"minecraft:used":{"minecraft:oak_trapdoor":8,"minecraft:cooked_mutton":3,"minecraft:stone_sword":2,"minecraft:cobblestone_stairs":18,"minecraft:ladder":3,"minecraft:oak_planks":2,"minecraft:chest":4,"minecraft:diamond_axe":83,"minecraft:oak_door":1,"minecraft:dirt":57,"minecraft:crafting_table":1,"minecraft:cobblestone_wall":5,"minecraft:oak_wood":1,"minecraft:granite":2,"minecraft:oak_log":20,"minecraft:diamond_pickaxe":729,"minecraft:diamond_shovel":759,"minecraft:oak_button":2,"minecraft:diamond_sword":40,"minecraft:cobblestone":137,"minecraft:furnace":1,"minecraft:glass_pane":8},"minecraft:dropped":{"minecraft:cobblestone":62,"minecraft:diamond_shovel":1,"minecraft:torch":7,"minecraft:oak_wood":6,"minecraft:diamond_pickaxe":1},"minecraft:mined":{"minecraft:diamond_ore":41,"minecraft:white_bed":1,"minecraft:cobblestone_stairs":2,"minecraft:cornflower":1,"minecraft:granite":24,"minecraft:oak_wood":1,"minecraft:grass_block":377,"minecraft:poppy":2,"minecraft:cobblestone":48,"minecraft:tall_grass":8,"minecraft:diorite":18,"minecraft:sandstone":5,"minecraft:redstone_ore":9,"minecraft:cobblestone_wall":1,"minecraft:birch_log":19,"minecraft:iron_ore":25,"minecraft:andesite":49,"minecraft:birch_leaves":1,"minecraft:grass_path":1,"minecraft:grass":92,"minecraft:oak_log":42,"minecraft:coal_ore":21,"minecraft:gravel":9,"minecraft:sand":21,"minecraft:dirt":369,"minecraft:stone":481,"minecraft:oak_leaves":14},"minecraft:crafted":{"minecraft:oak_door":3,"minecraft:oak_planks":120,"minecraft:crafting_table":1,"minecraft:furnace":1,"minecraft:cobblestone_stairs":16,"minecraft:oak_wood":3,"minecraft:diamond_shovel":1,"minecraft:birch_planks":76,"minecraft:air":0,"minecraft:glass_pane":32,"minecraft:oak_trapdoor":8,"minecraft:glass":12,"minecraft:diamond_pickaxe":1,"minecraft:ladder":3,"minecraft:stick":16,"minecraft:cobblestone_wall":6,"minecraft:chest":4,"minecraft:oak_button":2},"minecraft:killed":{"minecraft:creeper":1,"minecraft:skeleton":3,"minecraft:zombie":3,"minecraft:cow":1},"minecraft:picked_up":{"minecraft:birch_log":19,"minecraft:andesite":49,"minecraft:oak_log":50,"minecraft:cobblestone_wall":1,"minecraft:gunpowder":2,"minecraft:cobblestone_stairs":9,"minecraft:dirt":746,"minecraft:apple":3,"minecraft:wheat_seeds":12,"minecraft:beef":1,"minecraft:iron_ore":25,"minecraft:poppy":2,"minecraft:birch_sapling":1,"minecraft:oak_planks":56,"minecraft:stick":25,"minecraft:sandstone":5,"minecraft:torch":7,"minecraft:gravel":8,"minecraft:sand":21,"minecraft:diorite":18,"minecraft:white_bed":1,"minecraft:redstone":9,"minecraft:oak_wood":7,"minecraft:diamond_shovel":1,"minecraft:diamond":39,"minecraft:granite":6,"minecraft:oak_sapling":25,"minecraft:coal":20,"minecraft:cobblestone":497,"minecraft:diamond_pickaxe":2}},"DataVersion":2567}